{
  "is_parallel": false,
  "stop_time": 300000000000000,
  "nodes": [
    { "name": "valrose", "type": "QuantumRouter", "seed": 1, "memo_size": 20 },
    { "name": "ecov",    "type": "QuantumRouter", "seed": 2, "memo_size": 30 },
    { "name": "sophia",  "type": "QuantumRouter", "seed": 3, "memo_size": 20 },
    { "name": "antibes", "type": "QuantumRouter", "seed": 4, "memo_size": 20 },
    { "name": "grasse",  "type": "QuantumRouter", "seed": 5, "memo_size": 20 }
  ],
  "qconnections": [
  { "node1":"valrose","node2":"sophia",   "attenuation":0.00018, "distance": 25800,  "type": "meet_in_the_middle" },
  { "node1":"sophia",  "node2":"ecov",  "attenuation":0.00022, "distance": 22000, "type": "meet_in_the_middle" },
  { "node1":"sophia",  "node2":"antibes", "attenuation":0.00020, "distance": 11200, "type": "meet_in_the_middle" },
  { "node1": "sophia",    "node2": "grasse",  "attenuation": 0.00028, "distance": 14500, "type": "meet_in_the_middle" }
  
],
  "cconnections": [
    { "node1": "sophia", "node2": "ecov",    "delay": 119742536 },
    { "node1": "sophia", "node2": "antibes", "delay": 66850746 },
    { "node1": "sophia", "node2": "grasse",  "delay": 83012126 },
    { "node1": "sophia", "node2": "valrose", "delay": 138352611 }
  ]
}